setup.py
shinkenplugins/__init__.py
shinkenplugins.plugins.snmp_interface.egg-info/PKG-INFO
shinkenplugins.plugins.snmp_interface.egg-info/SOURCES.txt
shinkenplugins.plugins.snmp_interface.egg-info/dependency_links.txt
shinkenplugins.plugins.snmp_interface.egg-info/entry_points.txt
shinkenplugins.plugins.snmp_interface.egg-info/namespace_packages.txt
shinkenplugins.plugins.snmp_interface.egg-info/requires.txt
shinkenplugins.plugins.snmp_interface.egg-info/top_level.txt
shinkenplugins/plugins/__init__.py
shinkenplugins/plugins/snmp_interface/__init__.py
shinkenplugins/plugins/snmp_interface/snmp_interface.py